pyut2xml/__init__.py
pyut2xml/_version.py
pyut2xml/pyut2xml.py
pyut2xml/xml2pyut.py
pyut2xml/resources/__init__.py
pyut2xml/resources/loggingConfiguration.json
pyut2xml-1.0.0.dist-info/licenses/LICENSE
pyut2xml-1.0.0.dist-info/METADATA
pyut2xml-1.0.0.dist-info/WHEEL
pyut2xml-1.0.0.dist-info/entry_points.txt
pyut2xml-1.0.0.dist-info/top_level.txt
pyut2xml-1.0.0.dist-info/RECORD
